bismuthclient/__init__.py
bismuthclient/async_client.py
bismuthclient/bismuthapi.py
bismuthclient/bismuthclient.py
bismuthclient/bismuthcrypto.py
bismuthclient/bismuthformat.py
bismuthclient/bismuthmultiwallet.py
bismuthclient/bismuthutil.py
bismuthclient/bismuthwallet.py
bismuthclient/log.py
bismuthclient/lwbench.py
bismuthclient/quantizer.py
bismuthclient/rpcconnections.py
bismuthclient/simplecrypt.py
bismuthclient-0.0.53.dist-info/AUTHORS.rst
bismuthclient-0.0.53.dist-info/LICENSE
bismuthclient-0.0.53.dist-info/METADATA
bismuthclient-0.0.53.dist-info/WHEEL
bismuthclient-0.0.53.dist-info/top_level.txt
bismuthclient-0.0.53.dist-info/RECORD
