Metadata-Version: 2.1
Name: bismuthclient
Version: 0.0.53
Summary: Bismuth python library to be used by dApps and clients.
Home-page: https://github.com/BismuthFoundation/bismuthclient
Author: EggdraSyl Bismuth Foundation
Author-email: dev@eggpool.net
License: MIT license
Keywords: bismuthclient
Platform: UNKNOWN
Classifier: Development Status :: 2 - Pre-Alpha
Classifier: Intended Audience :: Developers
Classifier: License :: OSI Approved :: MIT License
Classifier: Natural Language :: English
Classifier: Programming Language :: Python :: 3.5
Classifier: Programming Language :: Python :: 3.6
Classifier: Programming Language :: Python :: 3.7
Requires-Dist: polysign
Requires-Dist: pycryptodomex
Requires-Dist: requests
